{
  "id": 1,
  "name": "Amhurst Road",
  "agent": {
    "name": "Felicity J Lord",
    "url": "http://www.fjlord.co.uk/",
    "contactName": "Dave Daveson",
    "contactPhone": "0800 00 10 66"
  },
  "location": {
    "name": "Amhurst Rd, Dalston, E8",
    "latitude": 51.548519,
    "longitude": -0.057968
  },
  "photos": [
    {
      "url": "http://bukk.it/cabinparty.gif",
      "caption": "i like turtles",
      "source": "agent"
    },
    {
      "url": "http://bukk.it/casualfriday.jpg",
      "caption": "i also like turtles",
      "source": "upload"
    }
  ],
  "enquired": true,
  "agentReplied": false,
  "viewed": false,
  "liked": false,
  "disliked": false
}